odoo/addons/website_sale_order_type/README.rst
odoo/addons/website_sale_order_type/__init__.py
odoo/addons/website_sale_order_type/__manifest__.py
odoo/addons/website_sale_order_type/i18n/ca.po
odoo/addons/website_sale_order_type/i18n/es.po
odoo/addons/website_sale_order_type/i18n/it.po
odoo/addons/website_sale_order_type/i18n/pt_BR.po
odoo/addons/website_sale_order_type/i18n/website_sale_order_type.pot
odoo/addons/website_sale_order_type/models/__init__.py
odoo/addons/website_sale_order_type/models/website.py
odoo/addons/website_sale_order_type/readme/CONTRIBUTORS.md
odoo/addons/website_sale_order_type/readme/DESCRIPTION.md
odoo/addons/website_sale_order_type/readme/USAGE.md
odoo/addons/website_sale_order_type/static/description/icon.png
odoo/addons/website_sale_order_type/static/description/index.html
odoo/addons/website_sale_order_type/static/tests/tours/website_sale_order_type_tour.esm.js
odoo/addons/website_sale_order_type/tests/__init__.py
odoo/addons/website_sale_order_type/tests/test_website_sale_order_type.py
odoo_addon_website_sale_order_type-18.0.1.0.0.3.dist-info/METADATA
odoo_addon_website_sale_order_type-18.0.1.0.0.3.dist-info/WHEEL
odoo_addon_website_sale_order_type-18.0.1.0.0.3.dist-info/top_level.txt
odoo_addon_website_sale_order_type-18.0.1.0.0.3.dist-info/RECORD
