Metadata-Version: 2.1
Name: odoo-addon-website_sale_order_type
Version: 18.0.1.0.0.3
Requires-Python: >=3.10
Requires-Dist: odoo-addon-sale_order_type==18.0.*
Requires-Dist: odoo==18.0.*
Summary: This module allows sale_order_type to work with website_sale.
Home-page: https://github.com/OCA/e-commerce
License: AGPL-3
Author: Agile Business Group, Odoo Community Association (OCA)
Author-email: support@odoo-community.org
Classifier: Programming Language :: Python
Classifier: Framework :: Odoo
Classifier: Framework :: Odoo :: 18.0
Classifier: License :: OSI Approved :: GNU Affero General Public License v3
Classifier: Development Status :: 4 - Beta
